convertunits/__init__.py
convertunits/area.py
convertunits/data_transfer_rate.py
convertunits/digital_storage.py
convertunits/energy.py
convertunits/frequency.py
convertunits/fuel_economy.py
convertunits/length.py
convertunits/mass.py
convertunits/plane_angle.py
convertunits/pressure.py
convertunits/speed.py
convertunits/temperature.py
convertunits/time.py
convertunits/utils.py
convertunits/volume.py
convertunits/formula/__init__.py
convertunits/formula/area/__init__.py
convertunits/formula/area/acre.py
convertunits/formula/area/hectare.py
convertunits/formula/area/square_foot.py
convertunits/formula/area/square_inch.py
convertunits/formula/area/square_kilometer.py
convertunits/formula/area/square_meter.py
convertunits/formula/area/square_mile.py
convertunits/formula/area/square_yard.py
convertunits/formula/data_transfer_rate/__init__.py
convertunits/formula/data_transfer_rate/bit_per_second.py
convertunits/formula/data_transfer_rate/gibibit_per_second.py
convertunits/formula/data_transfer_rate/gigabit_per_second.py
convertunits/formula/data_transfer_rate/gigabyte_per_second.py
convertunits/formula/data_transfer_rate/kibibit_per_second.py
convertunits/formula/data_transfer_rate/kilobit_per_second.py
convertunits/formula/data_transfer_rate/kilobyte_per_second.py
convertunits/formula/data_transfer_rate/mebibit_per_second.py
convertunits/formula/data_transfer_rate/megabit_per_second.py
convertunits/formula/data_transfer_rate/megabyte_per_second.py
convertunits/formula/data_transfer_rate/tebibit_per_second.py
convertunits/formula/data_transfer_rate/terabit_per_second.py
convertunits/formula/data_transfer_rate/terabyte_per_second.py
convertunits/formula/digital_storage/__init__.py
convertunits/formula/digital_storage/bit.py
convertunits/formula/digital_storage/byte.py
convertunits/formula/digital_storage/gibibit.py
convertunits/formula/digital_storage/gibibyte.py
convertunits/formula/digital_storage/gigabit.py
convertunits/formula/digital_storage/gigabyte.py
convertunits-1.0.4.dist-info/METADATA
convertunits-1.0.4.dist-info/WHEEL
convertunits-1.0.4.dist-info/top_level.txt
convertunits-1.0.4.dist-info/RECORD
