Metadata-Version: 2.1
Name: convertunits
Version: 1.0.4
Summary: Convert units in python.
Home-page: https://github.com/hostedposted/convertunits
Author: Hostedposted
Author-email: hostedpostedsite@gmail.com
License: UNKNOWN
Platform: UNKNOWN
Classifier: Programming Language :: Python :: 3.6
Classifier: Programming Language :: Python :: 3.7
Classifier: Programming Language :: Python :: 3.8
Classifier: Programming Language :: Python :: 3.9
Classifier: Operating System :: OS Independent
Classifier: License :: OSI Approved :: MIT License
Requires-Python: >=3.6
